{
  "gesture_name": "wrist_tilt_up_5",
  "repetition_index": 3,
  "start_time": "2026-05-29T16:45:09.952",
  "sample_rate_estimate": 48.132777688521955,
  "field_order": [
    "right_hand_x",
    "right_hand_y",
    "right_hand_z_mm",
    "right_hand_gesture",
    "left_hand_x",
    "left_hand_y",
    "left_hand_z_mm",
    "left_hand_gesture",
    "wrist_accel_x",
    "wrist_accel_y",
    "wrist_accel_z",
    "wrist_gyro_x",
    "wrist_gyro_y",
    "wrist_gyro_z",
    "wrist_pitch",
    "wrist_roll",
    "camdock_battery_level",
    "wristband_battery_level",
    "fans_battery_level",
    "keyboard_input",
    "keyboard_sensor_1_mm",
    "keyboard_sensor_2_mm",
    "keyboard_sensor_3_mm",
    "keyboard_sensor_4_mm",
    "charging_dock_input",
    "audiodock_input",
    "fans_input"
  ],
  "samples": [
    {
      "t_epoch": 1780053309.9525468,
      "t_rel": 0.0,
      "input_array": [
        null,
        null,
        0,
        null,
        null,
        null,
        858,
        null,
        1.716,
        9.993,
        3.403,
        9.046,
        -36.52,
        115.026,
        -9.24,
        71.19,
        6,
        42,
        null,
        "off",
        null,
        null,
        null,
        null,
        "TBD",
        "TBD",
        "off"
      ],
      "input_dict": {
        "right_hand_x": null,
        "right_hand_y": null,
        "right_hand_z_mm": 0,
        "right_hand_gesture": null,
        "left_hand_x": null,
        "left_hand_y": null,
        "left_hand_z_mm": 858,
        "left_hand_gesture": null,
        "wrist_accel_x": 1.716,
        "wrist_accel_y": 9.993,
        "wrist_accel_z": 3.403,
        "wrist_gyro_x": 9.046,
        "wrist_gyro_y": -36.52,
        "wrist_gyro_z": 115.026,
        "wrist_pitch": -9.24,
        "wrist_roll": 71.19,
        "camdock_battery_level": 6,
        "wristband_battery_level": 42,
        "fans_battery_level": null,
        "keyboard_input": "off",
        "keyboard_sensor_1_mm": null,
        "keyboard_sensor_2_mm": null,
        "keyboard_sensor_3_mm": null,
        "keyboard_sensor_4_mm": null,
        "charging_dock_input": "TBD",
        "audiodock_input": "TBD",
        "fans_input": "off"
      }
    },
    {
      "t_epoch": 1780053309.9775903,
      "t_rel": 0.025043487548828125,
      "input_array": [
        null,
        null,
        0,
        null,
        null,
        null,
        900,
        null,
        1.471,
        9.846,
        3.266,
        15.519,
        -26.078,
        116.805,
        -8.1,
        71.65,
        6,
        42,
        null,
        "off",
        null,
        null,
        null,
        null,
        "TBD",
        "TBD",
        "off"
      ],
      "input_dict": {
        "right_hand_x": null,
        "right_hand_y": null,
        "right_hand_z_mm": 0,
        "right_hand_gesture": null,
        "left_hand_x": null,
        "left_hand_y": null,
        "left_hand_z_mm": 900,
        "left_hand_gesture": null,
        "wrist_accel_x": 1.471,
        "wrist_accel_y": 9.846,
        "wrist_accel_z": 3.266,
        "wrist_gyro_x": 15.519,
        "wrist_gyro_y": -26.078,
        "wrist_gyro_z": 116.805,
        "wrist_pitch": -8.1,
        "wrist_roll": 71.65,
        "camdock_battery_level": 6,
        "wristband_battery_level": 42,
        "fans_battery_level": null,
        "keyboard_input": "off",
        "keyboard_sensor_1_mm": null,
        "keyboard_sensor_2_mm": null,
        "keyboard_sensor_3_mm": null,
        "keyboard_sensor_4_mm": null,
        "charging_dock_input": "TBD",
        "audiodock_input": "TBD",
        "fans_input": "off"
      }
    },
    {
      "t_epoch": 1780053309.9982002,
      "t_rel": 0.045653343200683594,
      "input_array": [
        null,
        null,
        0,
        null,
        null,
        null,
        900,
        null,
        1.471,
        9.846,
        3.266,
        15.519,
        -26.078,
        116.805,
        -8.1,
        71.65,
        6,
        42,
        null,
        "off",
        null,
        null,
        null,
        null,
        "TBD",
        "TBD",
        "off"
      ],
      "input_dict": {
        "right_hand_x": null,
        "right_hand_y": null,
        "right_hand_z_mm": 0,
        "right_hand_gesture": null,
        "left_hand_x": null,
        "left_hand_y": null,
        "left_hand_z_mm": 900,
        "left_hand_gesture": null,
        "wrist_accel_x": 1.471,
        "wrist_accel_y": 9.846,
        "wrist_accel_z": 3.266,
        "wrist_gyro_x": 15.519,
        "wrist_gyro_y": -26.078,
        "wrist_gyro_z": 116.805,
        "wrist_pitch": -8.1,
        "wrist_roll": 71.65,
        "camdock_battery_level": 6,
        "wristband_battery_level": 42,
        "fans_battery_level": null,
        "keyboard_input": "off",
        "keyboard_sensor_1_mm": null,
        "keyboard_sensor_2_mm": null,
        "keyboard_sensor_3_mm": null,
        "keyboard_sensor_4_mm": null,
        "charging_dock_input": "TBD",
        "audiodock_input": "TBD",
        "fans_input": "off"
      }
    },
    {
      "t_epoch": 1780053310.0191813,
      "t_rel": 0.0666344165802002,
      "input_array": [
        null,
        null,
        0,
        null,
        null,
        null,
        900,
        null,
        1.138,
        9.797,
        3.246,
        16.198,
        -22.62,
        117.965,
        -6.28,
        71.65,
        6,
        42,
        null,
        "off",
        null,
        null,
        null,
        null,
        "TBD",
        "TBD",
        "off"
      ],
      "input_dict": {
        "right_hand_x": null,
        "right_hand_y": null,
        "right_hand_z_mm": 0,
        "right_hand_gesture": null,
        "left_hand_x": null,
        "left_hand_y": null,
        "left_hand_z_mm": 900,
        "left_hand_gesture": null,
        "wrist_accel_x": 1.138,
        "wrist_accel_y": 9.797,
        "wrist_accel_z": 3.246,
        "wrist_gyro_x": 16.198,
        "wrist_gyro_y": -22.62,
        "wrist_gyro_z": 117.965,
        "wrist_pitch": -6.28,
        "wrist_roll": 71.65,
        "camdock_battery_level": 6,
        "wristband_battery_level": 42,
        "fans_battery_level": null,
        "keyboard_input": "off",
        "keyboard_sensor_1_mm": null,
        "keyboard_sensor_2_mm": null,
        "keyboard_sensor_3_mm": null,
        "keyboard_sensor_4_mm": null,
        "charging_dock_input": "TBD",
        "audiodock_input": "TBD",
        "fans_input": "off"
      }
    },
    {
      "t_epoch": 1780053310.0391836,
      "t_rel": 0.08663678169250488,
      "input_array": [
        null,
        null,
        0,
        null,
        null,
        null,
        928,
        null,
        1.128,
        9.709,
        3.364,
        15.313,
        -35.108,
        118.171,
        -6.25,
        70.89,
        6,
        42,
        null,
        "off",
        null,
        null,
        null,
        null,
        "TBD",
        "TBD",
        "off"
      ],
      "input_dict": {
        "right_hand_x": null,
        "right_hand_y": null,
        "right_hand_z_mm": 0,
        "right_hand_gesture": null,
        "left_hand_x": null,
        "left_hand_y": null,
        "left_hand_z_mm": 928,
        "left_hand_gesture": null,
        "wrist_accel_x": 1.128,
        "wrist_accel_y": 9.709,
        "wrist_accel_z": 3.364,
        "wrist_gyro_x": 15.313,
        "wrist_gyro_y": -35.108,
        "wrist_gyro_z": 118.171,
        "wrist_pitch": -6.25,
        "wrist_roll": 70.89,
        "camdock_battery_level": 6,
        "wristband_battery_level": 42,
        "fans_battery_level": null,
        "keyboard_input": "off",
        "keyboard_sensor_1_mm": null,
        "keyboard_sensor_2_mm": null,
        "keyboard_sensor_3_mm": null,
        "keyboard_sensor_4_mm": null,
        "charging_dock_input": "TBD",
        "audiodock_input": "TBD",
        "fans_input": "off"
      }
    },
    {
      "t_epoch": 1780053310.0621831,
      "t_rel": 0.10963630676269531,
      "input_array": [
        null,
        null,
        0,
        null,
        null,
        null,
        928,
        null,
        1.128,
        9.709,
        3.364,
        15.313,
        -35.108,
        118.171,
        -6.25,
        70.89,
        6,
        42,
        null,
        "off",
        null,
        null,
        null,
        null,
        "TBD",
        "TBD",
        "off"
      ],
      "input_dict": {
        "right_hand_x": null,
        "right_hand_y": null,
        "right_hand_z_mm": 0,
        "right_hand_gesture": null,
        "left_hand_x": null,
        "left_hand_y": null,
        "left_hand_z_mm": 928,
        "left_hand_gesture": null,
        "wrist_accel_x": 1.128,
        "wrist_accel_y": 9.709,
        "wrist_accel_z": 3.364,
        "wrist_gyro_x": 15.313,
        "wrist_gyro_y": -35.108,
        "wrist_gyro_z": 118.171,
        "wrist_pitch": -6.25,
        "wrist_roll": 70.89,
        "camdock_battery_level": 6,
        "wristband_battery_level": 42,
        "fans_battery_level": null,
        "keyboard_input": "off",
        "keyboard_sensor_1_mm": null,
        "keyboard_sensor_2_mm": null,
        "keyboard_sensor_3_mm": null,
        "keyboard_sensor_4_mm": null,
        "charging_dock_input": "TBD",
        "audiodock_input": "TBD",
        "fans_input": "off"
      }
    },
    {
      "t_epoch": 1780053310.0831861,
      "t_rel": 0.13063931465148926,
      "input_array": [
        null,
        null,
        0,
        null,
        null,
        null,
        928,
        null,
        1.971,
        9.787,
        3.285,
        16.458,
        -32.047,
        116.217,
        -10.81,
        71.44,
        6,
        42,
        null,
        "off",
        null,
        null,
        null,
        null,
        "TBD",
        "TBD",
        "off"
      ],
      "input_dict": {
        "right_hand_x": null,
        "right_hand_y": null,
        "right_hand_z_mm": 0,
        "right_hand_gesture": null,
        "left_hand_x": null,
        "left_hand_y": null,
        "left_hand_z_mm": 928,
        "left_hand_gesture": null,
        "wrist_accel_x": 1.971,
        "wrist_accel_y": 9.787,
        "wrist_accel_z": 3.285,
        "wrist_gyro_x": 16.458,
        "wrist_gyro_y": -32.047,
        "wrist_gyro_z": 116.217,
        "wrist_pitch": -10.81,
        "wrist_roll": 71.44,
        "camdock_battery_level": 6,
        "wristband_battery_level": 42,
        "fans_battery_level": null,
        "keyboard_input": "off",
        "keyboard_sensor_1_mm": null,
        "keyboard_sensor_2_mm": null,
        "keyboard_sensor_3_mm": null,
        "keyboard_sensor_4_mm": null,
        "charging_dock_input": "TBD",
        "audiodock_input": "TBD",
        "fans_input": "off"
      }
    },
    {
      "t_epoch": 1780053310.1032803,
      "t_rel": 0.15073347091674805,
      "input_array": [
        null,
        null,
        0,
        null,
        null,
        null,
        844,
        null,
        1.628,
        9.885,
        3.089,
        18.061,
        -24.948,
        114.523,
        -8.94,
        72.66,
        6,
        42,
        null,
        "off",
        null,
        null,
        null,
        null,
        "TBD",
        "TBD",
        "off"
      ],
      "input_dict": {
        "right_hand_x": null,
        "right_hand_y": null,
        "right_hand_z_mm": 0,
        "right_hand_gesture": null,
        "left_hand_x": null,
        "left_hand_y": null,
        "left_hand_z_mm": 844,
        "left_hand_gesture": null,
        "wrist_accel_x": 1.628,
        "wrist_accel_y": 9.885,
        "wrist_accel_z": 3.089,
        "wrist_gyro_x": 18.061,
        "wrist_gyro_y": -24.948,
        "wrist_gyro_z": 114.523,
        "wrist_pitch": -8.94,
        "wrist_roll": 72.66,
        "camdock_battery_level": 6,
        "wristband_battery_level": 42,
        "fans_battery_level": null,
        "keyboard_input": "off",
        "keyboard_sensor_1_mm": null,
        "keyboard_sensor_2_mm": null,
        "keyboard_sensor_3_mm": null,
        "keyboard_sensor_4_mm": null,
        "charging_dock_input": "TBD",
        "audiodock_input": "TBD",
        "fans_input": "off"
      }
    },
    {
      "t_epoch": 1780053310.12463,
      "t_rel": 0.17208313941955566,
      "input_array": [
        null,
        null,
        0,
        null,
        null,
        null,
        844,
        null,
        1.628,
        9.885,
        3.089,
        18.061,
        -24.948,
        114.523,
        -8.94,
        72.66,
        6,
        42,
        null,
        "off",
        null,
        null,
        null,
        null,
        "TBD",
        "TBD",
        "off"
      ],
      "input_dict": {
        "right_hand_x": null,
        "right_hand_y": null,
        "right_hand_z_mm": 0,
        "right_hand_gesture": null,
        "left_hand_x": null,
        "left_hand_y": null,
        "left_hand_z_mm": 844,
        "left_hand_gesture": null,
        "wrist_accel_x": 1.628,
        "wrist_accel_y": 9.885,
        "wrist_accel_z": 3.089,
        "wrist_gyro_x": 18.061,
        "wrist_gyro_y": -24.948,
        "wrist_gyro_z": 114.523,
        "wrist_pitch": -8.94,
        "wrist_roll": 72.66,
        "camdock_battery_level": 6,
        "wristband_battery_level": 42,
        "fans_battery_level": null,
        "keyboard_input": "off",
        "keyboard_sensor_1_mm": null,
        "keyboard_sensor_2_mm": null,
        "keyboard_sensor_3_mm": null,
        "keyboard_sensor_4_mm": null,
        "charging_dock_input": "TBD",
        "audiodock_input": "TBD",
        "fans_input": "off"
      }
    },
    {
      "t_epoch": 1780053310.1446657,
      "t_rel": 0.19211888313293457,
      "input_array": [
        null,
        null,
        0,
        null,
        null,
        null,
        844,
        null,
        1.628,
        9.885,
        3.089,
        18.061,
        -24.948,
        114.523,
        -8.94,
        72.66,
        6,
        42,
        null,
        "off",
        null,
        null,
        null,
        null,
        "TBD",
        "TBD",
        "off"
      ],
      "input_dict": {
        "right_hand_x": null,
        "right_hand_y": null,
        "right_hand_z_mm": 0,
        "right_hand_gesture": null,
        "left_hand_x": null,
        "left_hand_y": null,
        "left_hand_z_mm": 844,
        "left_hand_gesture": null,
        "wrist_accel_x": 1.628,
        "wrist_accel_y": 9.885,
        "wrist_accel_z": 3.089,
        "wrist_gyro_x": 18.061,
        "wrist_gyro_y": -24.948,
        "wrist_gyro_z": 114.523,
        "wrist_pitch": -8.94,
        "wrist_roll": 72.66,
        "camdock_battery_level": 6,
        "wristband_battery_level": 42,
        "fans_battery_level": null,
        "keyboard_input": "off",
        "keyboard_sensor_1_mm": null,
        "keyboard_sensor_2_mm": null,
        "keyboard_sensor_3_mm": null,
        "keyboard_sensor_4_mm": null,
        "charging_dock_input": "TBD",
        "audiodock_input": "TBD",
        "fans_input": "off"
      }
    },
    {
      "t_epoch": 1780053310.1656594,
      "t_rel": 0.21311259269714355,
      "input_array": [
        null,
        null,
        0,
        null,
        null,
        null,
        900,
        null,
        1.304,
        9.954,
        2.815,
        14.068,
        -28.223,
        114.851,
        -7.17,
        74.22,
        6,
        42,
        null,
        "off",
        null,
        null,
        null,
        null,
        "TBD",
        "TBD",
        "off"
      ],
      "input_dict": {
        "right_hand_x": null,
        "right_hand_y": null,
        "right_hand_z_mm": 0,
        "right_hand_gesture": null,
        "left_hand_x": null,
        "left_hand_y": null,
        "left_hand_z_mm": 900,
        "left_hand_gesture": null,
        "wrist_accel_x": 1.304,
        "wrist_accel_y": 9.954,
        "wrist_accel_z": 2.815,
        "wrist_gyro_x": 14.068,
        "wrist_gyro_y": -28.223,
        "wrist_gyro_z": 114.851,
        "wrist_pitch": -7.17,
        "wrist_roll": 74.22,
        "camdock_battery_level": 6,
        "wristband_battery_level": 42,
        "fans_battery_level": null,
        "keyboard_input": "off",
        "keyboard_sensor_1_mm": null,
        "keyboard_sensor_2_mm": null,
        "keyboard_sensor_3_mm": null,
        "keyboard_sensor_4_mm": null,
        "charging_dock_input": "TBD",
        "audiodock_input": "TBD",
        "fans_input": "off"
      }
    },
    {
      "t_epoch": 1780053310.1876855,
      "t_rel": 0.2351386547088623,
      "input_array": [
        null,
        null,
        0,
        null,
        null,
        null,
        900,
        null,
        1.304,
        9.954,
        2.815,
        14.068,
        -28.223,
        114.851,
        -7.17,
        74.22,
        6,
        42,
        null,
        "off",
        null,
        null,
        null,
        null,
        "TBD",
        "TBD",
        "off"
      ],
      "input_dict": {
        "right_hand_x": null,
        "right_hand_y": null,
        "right_hand_z_mm": 0,
        "right_hand_gesture": null,
        "left_hand_x": null,
        "left_hand_y": null,
        "left_hand_z_mm": 900,
        "left_hand_gesture": null,
        "wrist_accel_x": 1.304,
        "wrist_accel_y": 9.954,
        "wrist_accel_z": 2.815,
        "wrist_gyro_x": 14.068,
        "wrist_gyro_y": -28.223,
        "wrist_gyro_z": 114.851,
        "wrist_pitch": -7.17,
        "wrist_roll": 74.22,
        "camdock_battery_level": 6,
        "wristband_battery_level": 42,
        "fans_battery_level": null,
        "keyboard_input": "off",
        "keyboard_sensor_1_mm": null,
        "keyboard_sensor_2_mm": null,
        "keyboard_sensor_3_mm": null,
        "keyboard_sensor_4_mm": null,
        "charging_dock_input": "TBD",
        "audiodock_input": "TBD",
        "fans_input": "off"
      }
    },
    {
      "t_epoch": 1780053310.2081769,
      "t_rel": 0.2556300163269043,
      "input_array": [
        null,
        null,
        0,
        null,
        null,
        null,
        900,
        null,
        1.304,
        9.954,
        2.815,
        14.068,
        -28.223,
        114.851,
        -7.17,
        74.22,
        6,
        42,
        null,
        "off",
        null,
        null,
        null,
        null,
        "TBD",
        "TBD",
        "off"
      ],
      "input_dict": {
        "right_hand_x": null,
        "right_hand_y": null,
        "right_hand_z_mm": 0,
        "right_hand_gesture": null,
        "left_hand_x": null,
        "left_hand_y": null,
        "left_hand_z_mm": 900,
        "left_hand_gesture": null,
        "wrist_accel_x": 1.304,
        "wrist_accel_y": 9.954,
        "wrist_accel_z": 2.815,
        "wrist_gyro_x": 14.068,
        "wrist_gyro_y": -28.223,
        "wrist_gyro_z": 114.851,
        "wrist_pitch": -7.17,
        "wrist_roll": 74.22,
        "camdock_battery_level": 6,
        "wristband_battery_level": 42,
        "fans_battery_level": null,
        "keyboard_input": "off",
        "keyboard_sensor_1_mm": null,
        "keyboard_sensor_2_mm": null,
        "keyboard_sensor_3_mm": null,
        "keyboard_sensor_4_mm": null,
        "charging_dock_input": "TBD",
        "audiodock_input": "TBD",
        "fans_input": "off"
      }
    },
    {
      "t_epoch": 1780053310.2281806,
      "t_rel": 0.2756338119506836,
      "input_array": [
        null,
        null,
        0,
        null,
        null,
        null,
        900,
        null,
        1.344,
        10.003,
        2.667,
        13.641,
        -23.872,
        114.652,
        -7.38,
        75.07,
        6,
        42,
        null,
        "off",
        null,
        null,
        null,
        null,
        "TBD",
        "TBD",
        "off"
      ],
      "input_dict": {
        "right_hand_x": null,
        "right_hand_y": null,
        "right_hand_z_mm": 0,
        "right_hand_gesture": null,
        "left_hand_x": null,
        "left_hand_y": null,
        "left_hand_z_mm": 900,
        "left_hand_gesture": null,
        "wrist_accel_x": 1.344,
        "wrist_accel_y": 10.003,
        "wrist_accel_z": 2.667,
        "wrist_gyro_x": 13.641,
        "wrist_gyro_y": -23.872,
        "wrist_gyro_z": 114.652,
        "wrist_pitch": -7.38,
        "wrist_roll": 75.07,
        "camdock_battery_level": 6,
        "wristband_battery_level": 42,
        "fans_battery_level": null,
        "keyboard_input": "off",
        "keyboard_sensor_1_mm": null,
        "keyboard_sensor_2_mm": null,
        "keyboard_sensor_3_mm": null,
        "keyboard_sensor_4_mm": null,
        "charging_dock_input": "TBD",
        "audiodock_input": "TBD",
        "fans_input": "off"
      }
    },
    {
      "t_epoch": 1780053310.2491775,
      "t_rel": 0.2966306209564209,
      "input_array": [
        null,
        null,
        0,
        null,
        null,
        null,
        836,
        null,
        1.422,
        10.169,
        2.363,
        12.145,
        -24.459,
        113.797,
        -7.75,
        76.91,
        6,
        42,
        null,
        "off",
        null,
        null,
        null,
        null,
        "TBD",
        "TBD",
        "off"
      ],
      "input_dict": {
        "right_hand_x": null,
        "right_hand_y": null,
        "right_hand_z_mm": 0,
        "right_hand_gesture": null,
        "left_hand_x": null,
        "left_hand_y": null,
        "left_hand_z_mm": 836,
        "left_hand_gesture": null,
        "wrist_accel_x": 1.422,
        "wrist_accel_y": 10.169,
        "wrist_accel_z": 2.363,
        "wrist_gyro_x": 12.145,
        "wrist_gyro_y": -24.459,
        "wrist_gyro_z": 113.797,
        "wrist_pitch": -7.75,
        "wrist_roll": 76.91,
        "camdock_battery_level": 6,
        "wristband_battery_level": 42,
        "fans_battery_level": null,
        "keyboard_input": "off",
        "keyboard_sensor_1_mm": null,
        "keyboard_sensor_2_mm": null,
        "keyboard_sensor_3_mm": null,
        "keyboard_sensor_4_mm": null,
        "charging_dock_input": "TBD",
        "audiodock_input": "TBD",
        "fans_input": "off"
      }
    },
    {
      "t_epoch": 1780053310.2701786,
      "t_rel": 0.31763172149658203,
      "input_array": [
        null,
        null,
        0,
        null,
        null,
        null,
        836,
        null,
        1.422,
        10.169,
        2.363,
        12.145,
        -24.459,
        113.797,
        -7.75,
        76.91,
        6,
        42,
        null,
        "off",
        null,
        null,
        null,
        null,
        "TBD",
        "TBD",
        "off"
      ],
      "input_dict": {
        "right_hand_x": null,
        "right_hand_y": null,
        "right_hand_z_mm": 0,
        "right_hand_gesture": null,
        "left_hand_x": null,
        "left_hand_y": null,
        "left_hand_z_mm": 836,
        "left_hand_gesture": null,
        "wrist_accel_x": 1.422,
        "wrist_accel_y": 10.169,
        "wrist_accel_z": 2.363,
        "wrist_gyro_x": 12.145,
        "wrist_gyro_y": -24.459,
        "wrist_gyro_z": 113.797,
        "wrist_pitch": -7.75,
        "wrist_roll": 76.91,
        "camdock_battery_level": 6,
        "wristband_battery_level": 42,
        "fans_battery_level": null,
        "keyboard_input": "off",
        "keyboard_sensor_1_mm": null,
        "keyboard_sensor_2_mm": null,
        "keyboard_sensor_3_mm": null,
        "keyboard_sensor_4_mm": null,
        "charging_dock_input": "TBD",
        "audiodock_input": "TBD",
        "fans_input": "off"
      }
    },
    {
      "t_epoch": 1780053310.2901828,
      "t_rel": 0.33763599395751953,
      "input_array": [
        null,
        null,
        0,
        null,
        null,
        null,
        836,
        null,
        0.598,
        9.924,
        3.04,
        12.007,
        -40.001,
        113.683,
        -3.29,
        72.97,
        6,
        42,
        null,
        "off",
        null,
        null,
        null,
        null,
        "TBD",
        "TBD",
        "off"
      ],
      "input_dict": {
        "right_hand_x": null,
        "right_hand_y": null,
        "right_hand_z_mm": 0,
        "right_hand_gesture": null,
        "left_hand_x": null,
        "left_hand_y": null,
        "left_hand_z_mm": 836,
        "left_hand_gesture": null,
        "wrist_accel_x": 0.598,
        "wrist_accel_y": 9.924,
        "wrist_accel_z": 3.04,
        "wrist_gyro_x": 12.007,
        "wrist_gyro_y": -40.001,
        "wrist_gyro_z": 113.683,
        "wrist_pitch": -3.29,
        "wrist_roll": 72.97,
        "camdock_battery_level": 6,
        "wristband_battery_level": 42,
        "fans_battery_level": null,
        "keyboard_input": "off",
        "keyboard_sensor_1_mm": null,
        "keyboard_sensor_2_mm": null,
        "keyboard_sensor_3_mm": null,
        "keyboard_sensor_4_mm": null,
        "charging_dock_input": "TBD",
        "audiodock_input": "TBD",
        "fans_input": "off"
      }
    },
    {
      "t_epoch": 1780053310.3107111,
      "t_rel": 0.35816431045532227,
      "input_array": [
        null,
        null,
        0,
        null,
        null,
        null,
        875,
        null,
        1.108,
        9.885,
        2.893,
        11.801,
        -39.406,
        113.996,
        -6.12,
        73.7,
        6,
        42,
        null,
        "off",
        null,
        null,
        null,
        null,
        "TBD",
        "TBD",
        "off"
      ],
      "input_dict": {
        "right_hand_x": null,
        "right_hand_y": null,
        "right_hand_z_mm": 0,
        "right_hand_gesture": null,
        "left_hand_x": null,
        "left_hand_y": null,
        "left_hand_z_mm": 875,
        "left_hand_gesture": null,
        "wrist_accel_x": 1.108,
        "wrist_accel_y": 9.885,
        "wrist_accel_z": 2.893,
        "wrist_gyro_x": 11.801,
        "wrist_gyro_y": -39.406,
        "wrist_gyro_z": 113.996,
        "wrist_pitch": -6.12,
        "wrist_roll": 73.7,
        "camdock_battery_level": 6,
        "wristband_battery_level": 42,
        "fans_battery_level": null,
        "keyboard_input": "off",
        "keyboard_sensor_1_mm": null,
        "keyboard_sensor_2_mm": null,
        "keyboard_sensor_3_mm": null,
        "keyboard_sensor_4_mm": null,
        "charging_dock_input": "TBD",
        "audiodock_input": "TBD",
        "fans_input": "off"
      }
    },
    {
      "t_epoch": 1780053310.333323,
      "t_rel": 0.38077616691589355,
      "input_array": [
        null,
        null,
        0,
        null,
        null,
        null,
        875,
        null,
        1.108,
        9.885,
        2.893,
        11.801,
        -39.406,
        113.996,
        -6.12,
        73.7,
        6,
        42,
        null,
        "off",
        null,
        null,
        null,
        null,
        "TBD",
        "TBD",
        "off"
      ],
      "input_dict": {
        "right_hand_x": null,
        "right_hand_y": null,
        "right_hand_z_mm": 0,
        "right_hand_gesture": null,
        "left_hand_x": null,
        "left_hand_y": null,
        "left_hand_z_mm": 875,
        "left_hand_gesture": null,
        "wrist_accel_x": 1.108,
        "wrist_accel_y": 9.885,
        "wrist_accel_z": 2.893,
        "wrist_gyro_x": 11.801,
        "wrist_gyro_y": -39.406,
        "wrist_gyro_z": 113.996,
        "wrist_pitch": -6.12,
        "wrist_roll": 73.7,
        "camdock_battery_level": 6,
        "wristband_battery_level": 42,
        "fans_battery_level": null,
        "keyboard_input": "off",
        "keyboard_sensor_1_mm": null,
        "keyboard_sensor_2_mm": null,
        "keyboard_sensor_3_mm": null,
        "keyboard_sensor_4_mm": null,
        "charging_dock_input": "TBD",
        "audiodock_input": "TBD",
        "fans_input": "off"
      }
    },
    {
      "t_epoch": 1780053310.3534844,
      "t_rel": 0.400937557220459,
      "input_array": [
        null,
        null,
        0,
        null,
        null,
        null,
        875,
        null,
        1.608,
        10.13,
        2.589,
        15.275,
        -19.704,
        114.515,
        -8.74,
        75.68,
        6,
        42,
        null,
        "off",
        null,
        null,
        null,
        null,
        "TBD",
        "TBD",
        "off"
      ],
      "input_dict": {
        "right_hand_x": null,
        "right_hand_y": null,
        "right_hand_z_mm": 0,
        "right_hand_gesture": null,
        "left_hand_x": null,
        "left_hand_y": null,
        "left_hand_z_mm": 875,
        "left_hand_gesture": null,
        "wrist_accel_x": 1.608,
        "wrist_accel_y": 10.13,
        "wrist_accel_z": 2.589,
        "wrist_gyro_x": 15.275,
        "wrist_gyro_y": -19.704,
        "wrist_gyro_z": 114.515,
        "wrist_pitch": -8.74,
        "wrist_roll": 75.68,
        "camdock_battery_level": 6,
        "wristband_battery_level": 42,
        "fans_battery_level": null,
        "keyboard_input": "off",
        "keyboard_sensor_1_mm": null,
        "keyboard_sensor_2_mm": null,
        "keyboard_sensor_3_mm": null,
        "keyboard_sensor_4_mm": null,
        "charging_dock_input": "TBD",
        "audiodock_input": "TBD",
        "fans_input": "off"
      }
    },
    {
      "t_epoch": 1780053310.374491,
      "t_rel": 0.42194414138793945,
      "input_array": [
        null,
        null,
        0,
        null,
        null,
        null,
        947,
        null,
        0.412,
        9.905,
        3.158,
        14.099,
        -23.849,
        114.668,
        -2.26,
        72.34,
        6,
        42,
        null,
        "off",
        null,
        null,
        null,
        null,
        "TBD",
        "TBD",
        "off"
      ],
      "input_dict": {
        "right_hand_x": null,
        "right_hand_y": null,
        "right_hand_z_mm": 0,
        "right_hand_gesture": null,
        "left_hand_x": null,
        "left_hand_y": null,
        "left_hand_z_mm": 947,
        "left_hand_gesture": null,
        "wrist_accel_x": 0.412,
        "wrist_accel_y": 9.905,
        "wrist_accel_z": 3.158,
        "wrist_gyro_x": 14.099,
        "wrist_gyro_y": -23.849,
        "wrist_gyro_z": 114.668,
        "wrist_pitch": -2.26,
        "wrist_roll": 72.34,
        "camdock_battery_level": 6,
        "wristband_battery_level": 42,
        "fans_battery_level": null,
        "keyboard_input": "off",
        "keyboard_sensor_1_mm": null,
        "keyboard_sensor_2_mm": null,
        "keyboard_sensor_3_mm": null,
        "keyboard_sensor_4_mm": null,
        "charging_dock_input": "TBD",
        "audiodock_input": "TBD",
        "fans_input": "off"
      }
    },
    {
      "t_epoch": 1780053310.3949778,
      "t_rel": 0.4424309730529785,
      "input_array": [
        null,
        null,
        0,
        null,
        null,
        null,
        947,
        null,
        0.412,
        9.905,
        3.158,
        14.099,
        -23.849,
        114.668,
        -2.26,
        72.34,
        6,
        42,
        null,
        "off",
        null,
        null,
        null,
        null,
        "TBD",
        "TBD",
        "off"
      ],
      "input_dict": {
        "right_hand_x": null,
        "right_hand_y": null,
        "right_hand_z_mm": 0,
        "right_hand_gesture": null,
        "left_hand_x": null,
        "left_hand_y": null,
        "left_hand_z_mm": 947,
        "left_hand_gesture": null,
        "wrist_accel_x": 0.412,
        "wrist_accel_y": 9.905,
        "wrist_accel_z": 3.158,
        "wrist_gyro_x": 14.099,
        "wrist_gyro_y": -23.849,
        "wrist_gyro_z": 114.668,
        "wrist_pitch": -2.26,
        "wrist_roll": 72.34,
        "camdock_battery_level": 6,
        "wristband_battery_level": 42,
        "fans_battery_level": null,
        "keyboard_input": "off",
        "keyboard_sensor_1_mm": null,
        "keyboard_sensor_2_mm": null,
        "keyboard_sensor_3_mm": null,
        "keyboard_sensor_4_mm": null,
        "charging_dock_input": "TBD",
        "audiodock_input": "TBD",
        "fans_input": "off"
      }
    },
    {
      "t_epoch": 1780053310.4149988,
      "t_rel": 0.4624519348144531,
      "input_array": [
        null,
        null,
        0,
        null,
        null,
        null,
        896,
        null,
        1.04,
        9.934,
        2.903,
        12.42,
        -30.238,
        115.202,
        -5.75,
        73.69,
        6,
        42,
        null,
        "off",
        null,
        null,
        null,
        null,
        "TBD",
        "TBD",
        "off"
      ],
      "input_dict": {
        "right_hand_x": null,
        "right_hand_y": null,
        "right_hand_z_mm": 0,
        "right_hand_gesture": null,
        "left_hand_x": null,
        "left_hand_y": null,
        "left_hand_z_mm": 896,
        "left_hand_gesture": null,
        "wrist_accel_x": 1.04,
        "wrist_accel_y": 9.934,
        "wrist_accel_z": 2.903,
        "wrist_gyro_x": 12.42,
        "wrist_gyro_y": -30.238,
        "wrist_gyro_z": 115.202,
        "wrist_pitch": -5.75,
        "wrist_roll": 73.69,
        "camdock_battery_level": 6,
        "wristband_battery_level": 42,
        "fans_battery_level": null,
        "keyboard_input": "off",
        "keyboard_sensor_1_mm": null,
        "keyboard_sensor_2_mm": null,
        "keyboard_sensor_3_mm": null,
        "keyboard_sensor_4_mm": null,
        "charging_dock_input": "TBD",
        "audiodock_input": "TBD",
        "fans_input": "off"
      }
    },
    {
      "t_epoch": 1780053310.4350984,
      "t_rel": 0.48255157470703125,
      "input_array": [
        null,
        null,
        0,
        null,
        null,
        null,
        896,
        null,
        1.049,
        10.022,
        2.824,
        12.87,
        -34.162,
        113.942,
        -5.75,
        74.24,
        6,
        42,
        null,
        "off",
        null,
        null,
        null,
        null,
        "TBD",
        "TBD",
        "off"
      ],
      "input_dict": {
        "right_hand_x": null,
        "right_hand_y": null,
        "right_hand_z_mm": 0,
        "right_hand_gesture": null,
        "left_hand_x": null,
        "left_hand_y": null,
        "left_hand_z_mm": 896,
        "left_hand_gesture": null,
        "wrist_accel_x": 1.049,
        "wrist_accel_y": 10.022,
        "wrist_accel_z": 2.824,
        "wrist_gyro_x": 12.87,
        "wrist_gyro_y": -34.162,
        "wrist_gyro_z": 113.942,
        "wrist_pitch": -5.75,
        "wrist_roll": 74.24,
        "camdock_battery_level": 6,
        "wristband_battery_level": 42,
        "fans_battery_level": null,
        "keyboard_input": "off",
        "keyboard_sensor_1_mm": null,
        "keyboard_sensor_2_mm": null,
        "keyboard_sensor_3_mm": null,
        "keyboard_sensor_4_mm": null,
        "charging_dock_input": "TBD",
        "audiodock_input": "TBD",
        "fans_input": "off"
      }
    },
    {
      "t_epoch": 1780053310.4559972,
      "t_rel": 0.5034503936767578,
      "input_array": [
        null,
        null,
        0,
        null,
        null,
        null,
        896,
        null,
        1.049,
        10.022,
        2.824,
        12.87,
        -34.162,
        113.942,
        -5.75,
        74.24,
        6,
        42,
        null,
        "off",
        null,
        null,
        null,
        null,
        "TBD",
        "TBD",
        "off"
      ],
      "input_dict": {
        "right_hand_x": null,
        "right_hand_y": null,
        "right_hand_z_mm": 0,
        "right_hand_gesture": null,
        "left_hand_x": null,
        "left_hand_y": null,
        "left_hand_z_mm": 896,
        "left_hand_gesture": null,
        "wrist_accel_x": 1.049,
        "wrist_accel_y": 10.022,
        "wrist_accel_z": 2.824,
        "wrist_gyro_x": 12.87,
        "wrist_gyro_y": -34.162,
        "wrist_gyro_z": 113.942,
        "wrist_pitch": -5.75,
        "wrist_roll": 74.24,
        "camdock_battery_level": 6,
        "wristband_battery_level": 42,
        "fans_battery_level": null,
        "keyboard_input": "off",
        "keyboard_sensor_1_mm": null,
        "keyboard_sensor_2_mm": null,
        "keyboard_sensor_3_mm": null,
        "keyboard_sensor_4_mm": null,
        "charging_dock_input": "TBD",
        "audiodock_input": "TBD",
        "fans_input": "off"
      }
    },
    {
      "t_epoch": 1780053310.4761026,
      "t_rel": 0.5235557556152344,
      "input_array": [
        null,
        null,
        0,
        null,
        null,
        null,
        874,
        null,
        1.138,
        10.052,
        2.677,
        11.061,
        -34.238,
        113.553,
        -6.25,
        75.1,
        6,
        42,
        null,
        "off",
        null,
        null,
        null,
        null,
        "TBD",
        "TBD",
        "off"
      ],
      "input_dict": {
        "right_hand_x": null,
        "right_hand_y": null,
        "right_hand_z_mm": 0,
        "right_hand_gesture": null,
        "left_hand_x": null,
        "left_hand_y": null,
        "left_hand_z_mm": 874,
        "left_hand_gesture": null,
        "wrist_accel_x": 1.138,
        "wrist_accel_y": 10.052,
        "wrist_accel_z": 2.677,
        "wrist_gyro_x": 11.061,
        "wrist_gyro_y": -34.238,
        "wrist_gyro_z": 113.553,
        "wrist_pitch": -6.25,
        "wrist_roll": 75.1,
        "camdock_battery_level": 6,
        "wristband_battery_level": 42,
        "fans_battery_level": null,
        "keyboard_input": "off",
        "keyboard_sensor_1_mm": null,
        "keyboard_sensor_2_mm": null,
        "keyboard_sensor_3_mm": null,
        "keyboard_sensor_4_mm": null,
        "charging_dock_input": "TBD",
        "audiodock_input": "TBD",
        "fans_input": "off"
      }
    },
    {
      "t_epoch": 1780053310.4968243,
      "t_rel": 0.5442774295806885,
      "input_array": [
        null,
        null,
        0,
        null,
        null,
        null,
        874,
        null,
        1.363,
        10.013,
        2.716,
        11.664,
        -28.452,
        114.912,
        -7.49,
        74.83,
        6,
        42,
        null,
        "off",
        null,
        null,
        null,
        null,
        "TBD",
        "TBD",
        "off"
      ],
      "input_dict": {
        "right_hand_x": null,
        "right_hand_y": null,
        "right_hand_z_mm": 0,
        "right_hand_gesture": null,
        "left_hand_x": null,
        "left_hand_y": null,
        "left_hand_z_mm": 874,
        "left_hand_gesture": null,
        "wrist_accel_x": 1.363,
        "wrist_accel_y": 10.013,
        "wrist_accel_z": 2.716,
        "wrist_gyro_x": 11.664,
        "wrist_gyro_y": -28.452,
        "wrist_gyro_z": 114.912,
        "wrist_pitch": -7.49,
        "wrist_roll": 74.83,
        "camdock_battery_level": 6,
        "wristband_battery_level": 42,
        "fans_battery_level": null,
        "keyboard_input": "off",
        "keyboard_sensor_1_mm": null,
        "keyboard_sensor_2_mm": null,
        "keyboard_sensor_3_mm": null,
        "keyboard_sensor_4_mm": null,
        "charging_dock_input": "TBD",
        "audiodock_input": "TBD",
        "fans_input": "off"
      }
    },
    {
      "t_epoch": 1780053310.5178235,
      "t_rel": 0.5652766227722168,
      "input_array": [
        null,
        null,
        0,
        null,
        null,
        null,
        874,
        null,
        1.363,
        10.013,
        2.716,
        11.664,
        -28.452,
        114.912,
        -7.49,
        74.83,
        6,
        42,
        null,
        "off",
        null,
        null,
        null,
        null,
        "TBD",
        "TBD",
        "off"
      ],
      "input_dict": {
        "right_hand_x": null,
        "right_hand_y": null,
        "right_hand_z_mm": 0,
        "right_hand_gesture": null,
        "left_hand_x": null,
        "left_hand_y": null,
        "left_hand_z_mm": 874,
        "left_hand_gesture": null,
        "wrist_accel_x": 1.363,
        "wrist_accel_y": 10.013,
        "wrist_accel_z": 2.716,
        "wrist_gyro_x": 11.664,
        "wrist_gyro_y": -28.452,
        "wrist_gyro_z": 114.912,
        "wrist_pitch": -7.49,
        "wrist_roll": 74.83,
        "camdock_battery_level": 6,
        "wristband_battery_level": 42,
        "fans_battery_level": null,
        "keyboard_input": "off",
        "keyboard_sensor_1_mm": null,
        "keyboard_sensor_2_mm": null,
        "keyboard_sensor_3_mm": null,
        "keyboard_sensor_4_mm": null,
        "charging_dock_input": "TBD",
        "audiodock_input": "TBD",
        "fans_input": "off"
      }
    },
    {
      "t_epoch": 1780053310.5378683,
      "t_rel": 0.5853214263916016,
      "input_array": [
        null,
        null,
        0,
        null,
        null,
        null,
        874,
        null,
        1.363,
        10.013,
        2.716,
        11.664,
        -28.452,
        114.912,
        -7.49,
        74.83,
        6,
        42,
        null,
        "off",
        null,
        null,
        null,
        null,
        "TBD",
        "TBD",
        "off"
      ],
      "input_dict": {
        "right_hand_x": null,
        "right_hand_y": null,
        "right_hand_z_mm": 0,
        "right_hand_gesture": null,
        "left_hand_x": null,
        "left_hand_y": null,
        "left_hand_z_mm": 874,
        "left_hand_gesture": null,
        "wrist_accel_x": 1.363,
        "wrist_accel_y": 10.013,
        "wrist_accel_z": 2.716,
        "wrist_gyro_x": 11.664,
        "wrist_gyro_y": -28.452,
        "wrist_gyro_z": 114.912,
        "wrist_pitch": -7.49,
        "wrist_roll": 74.83,
        "camdock_battery_level": 6,
        "wristband_battery_level": 42,
        "fans_battery_level": null,
        "keyboard_input": "off",
        "keyboard_sensor_1_mm": null,
        "keyboard_sensor_2_mm": null,
        "keyboard_sensor_3_mm": null,
        "keyboard_sensor_4_mm": null,
        "charging_dock_input": "TBD",
        "audiodock_input": "TBD",
        "fans_input": "off"
      }
    },
    {
      "t_epoch": 1780053310.5588362,
      "t_rel": 0.6062893867492676,
      "input_array": [
        null,
        null,
        0,
        null,
        null,
        null,
        858,
        null,
        0.657,
        9.973,
        2.579,
        13.343,
        -29.917,
        114.507,
        -3.65,
        75.5,
        6,
        42,
        null,
        "off",
        null,
        null,
        null,
        null,
        "TBD",
        "TBD",
        "off"
      ],
      "input_dict": {
        "right_hand_x": null,
        "right_hand_y": null,
        "right_hand_z_mm": 0,
        "right_hand_gesture": null,
        "left_hand_x": null,
        "left_hand_y": null,
        "left_hand_z_mm": 858,
        "left_hand_gesture": null,
        "wrist_accel_x": 0.657,
        "wrist_accel_y": 9.973,
        "wrist_accel_z": 2.579,
        "wrist_gyro_x": 13.343,
        "wrist_gyro_y": -29.917,
        "wrist_gyro_z": 114.507,
        "wrist_pitch": -3.65,
        "wrist_roll": 75.5,
        "camdock_battery_level": 6,
        "wristband_battery_level": 42,
        "fans_battery_level": null,
        "keyboard_input": "off",
        "keyboard_sensor_1_mm": null,
        "keyboard_sensor_2_mm": null,
        "keyboard_sensor_3_mm": null,
        "keyboard_sensor_4_mm": null,
        "charging_dock_input": "TBD",
        "audiodock_input": "TBD",
        "fans_input": "off"
      }
    },
    {
      "t_epoch": 1780053310.5798275,
      "t_rel": 0.6272807121276855,
      "input_array": [
        null,
        null,
        0,
        null,
        null,
        null,
        858,
        null,
        1.128,
        10.032,
        2.628,
        12.259,
        -34.841,
        113.232,
        -6.2,
        75.32,
        6,
        42,
        null,
        "off",
        null,
        null,
        null,
        null,
        "TBD",
        "TBD",
        "off"
      ],
      "input_dict": {
        "right_hand_x": null,
        "right_hand_y": null,
        "right_hand_z_mm": 0,
        "right_hand_gesture": null,
        "left_hand_x": null,
        "left_hand_y": null,
        "left_hand_z_mm": 858,
        "left_hand_gesture": null,
        "wrist_accel_x": 1.128,
        "wrist_accel_y": 10.032,
        "wrist_accel_z": 2.628,
        "wrist_gyro_x": 12.259,
        "wrist_gyro_y": -34.841,
        "wrist_gyro_z": 113.232,
        "wrist_pitch": -6.2,
        "wrist_roll": 75.32,
        "camdock_battery_level": 6,
        "wristband_battery_level": 42,
        "fans_battery_level": null,
        "keyboard_input": "off",
        "keyboard_sensor_1_mm": null,
        "keyboard_sensor_2_mm": null,
        "keyboard_sensor_3_mm": null,
        "keyboard_sensor_4_mm": null,
        "charging_dock_input": "TBD",
        "audiodock_input": "TBD",
        "fans_input": "off"
      }
    },
    {
      "t_epoch": 1780053310.6005626,
      "t_rel": 0.6480157375335693,
      "input_array": [
        null,
        null,
        0,
        null,
        null,
        null,
        858,
        null,
        1.128,
        10.032,
        2.628,
        12.259,
        -34.841,
        113.232,
        -6.2,
        75.32,
        6,
        42,
        null,
        "off",
        null,
        null,
        null,
        null,
        "TBD",
        "TBD",
        "off"
      ],
      "input_dict": {
        "right_hand_x": null,
        "right_hand_y": null,
        "right_hand_z_mm": 0,
        "right_hand_gesture": null,
        "left_hand_x": null,
        "left_hand_y": null,
        "left_hand_z_mm": 858,
        "left_hand_gesture": null,
        "wrist_accel_x": 1.128,
        "wrist_accel_y": 10.032,
        "wrist_accel_z": 2.628,
        "wrist_gyro_x": 12.259,
        "wrist_gyro_y": -34.841,
        "wrist_gyro_z": 113.232,
        "wrist_pitch": -6.2,
        "wrist_roll": 75.32,
        "camdock_battery_level": 6,
        "wristband_battery_level": 42,
        "fans_battery_level": null,
        "keyboard_input": "off",
        "keyboard_sensor_1_mm": null,
        "keyboard_sensor_2_mm": null,
        "keyboard_sensor_3_mm": null,
        "keyboard_sensor_4_mm": null,
        "charging_dock_input": "TBD",
        "audiodock_input": "TBD",
        "fans_input": "off"
      }
    },
    {
      "t_epoch": 1780053310.621561,
      "t_rel": 0.6690142154693604,
      "input_array": [
        null,
        null,
        0,
        null,
        null,
        null,
        902,
        null,
        1.03,
        10.013,
        2.893,
        13.58,
        -34.154,
        112.973,
        -5.63,
        73.9,
        5,
        42,
        null,
        "off",
        null,
        null,
        null,
        null,
        "TBD",
        "TBD",
        "off"
      ],
      "input_dict": {
        "right_hand_x": null,
        "right_hand_y": null,
        "right_hand_z_mm": 0,
        "right_hand_gesture": null,
        "left_hand_x": null,
        "left_hand_y": null,
        "left_hand_z_mm": 902,
        "left_hand_gesture": null,
        "wrist_accel_x": 1.03,
        "wrist_accel_y": 10.013,
        "wrist_accel_z": 2.893,
        "wrist_gyro_x": 13.58,
        "wrist_gyro_y": -34.154,
        "wrist_gyro_z": 112.973,
        "wrist_pitch": -5.63,
        "wrist_roll": 73.9,
        "camdock_battery_level": 5,
        "wristband_battery_level": 42,
        "fans_battery_level": null,
        "keyboard_input": "off",
        "keyboard_sensor_1_mm": null,
        "keyboard_sensor_2_mm": null,
        "keyboard_sensor_3_mm": null,
        "keyboard_sensor_4_mm": null,
        "charging_dock_input": "TBD",
        "audiodock_input": "TBD",
        "fans_input": "off"
      }
    },
    {
      "t_epoch": 1780053310.6424499,
      "t_rel": 0.6899030208587646,
      "input_array": [
        null,
        null,
        0,
        null,
        null,
        null,
        902,
        null,
        0.951,
        10.071,
        2.834,
        13.595,
        -39.047,
        112.484,
        -5.21,
        74.29,
        5,
        42,
        null,
        "off",
        null,
        null,
        null,
        null,
        "TBD",
        "TBD",
        "off"
      ],
      "input_dict": {
        "right_hand_x": null,
        "right_hand_y": null,
        "right_hand_z_mm": 0,
        "right_hand_gesture": null,
        "left_hand_x": null,
        "left_hand_y": null,
        "left_hand_z_mm": 902,
        "left_hand_gesture": null,
        "wrist_accel_x": 0.951,
        "wrist_accel_y": 10.071,
        "wrist_accel_z": 2.834,
        "wrist_gyro_x": 13.595,
        "wrist_gyro_y": -39.047,
        "wrist_gyro_z": 112.484,
        "wrist_pitch": -5.21,
        "wrist_roll": 74.29,
        "camdock_battery_level": 5,
        "wristband_battery_level": 42,
        "fans_battery_level": null,
        "keyboard_input": "off",
        "keyboard_sensor_1_mm": null,
        "keyboard_sensor_2_mm": null,
        "keyboard_sensor_3_mm": null,
        "keyboard_sensor_4_mm": null,
        "charging_dock_input": "TBD",
        "audiodock_input": "TBD",
        "fans_input": "off"
      }
    },
    {
      "t_epoch": 1780053310.662453,
      "t_rel": 0.7099061012268066,
      "input_array": [
        null,
        null,
        0,
        null,
        null,
        null,
        902,
        null,
        0.951,
        10.071,
        2.834,
        13.595,
        -39.047,
        112.484,
        -5.21,
        74.29,
        5,
        42,
        null,
        "off",
        null,
        null,
        null,
        null,
        "TBD",
        "TBD",
        "off"
      ],
      "input_dict": {
        "right_hand_x": null,
        "right_hand_y": null,
        "right_hand_z_mm": 0,
        "right_hand_gesture": null,
        "left_hand_x": null,
        "left_hand_y": null,
        "left_hand_z_mm": 902,
        "left_hand_gesture": null,
        "wrist_accel_x": 0.951,
        "wrist_accel_y": 10.071,
        "wrist_accel_z": 2.834,
        "wrist_gyro_x": 13.595,
        "wrist_gyro_y": -39.047,
        "wrist_gyro_z": 112.484,
        "wrist_pitch": -5.21,
        "wrist_roll": 74.29,
        "camdock_battery_level": 5,
        "wristband_battery_level": 42,
        "fans_battery_level": null,
        "keyboard_input": "off",
        "keyboard_sensor_1_mm": null,
        "keyboard_sensor_2_mm": null,
        "keyboard_sensor_3_mm": null,
        "keyboard_sensor_4_mm": null,
        "charging_dock_input": "TBD",
        "audiodock_input": "TBD",
        "fans_input": "off"
      }
    },
    {
      "t_epoch": 1780053310.6824574,
      "t_rel": 0.7299106121063232,
      "input_array": [
        null,
        null,
        0,
        null,
        null,
        null,
        902,
        null,
        0.951,
        10.071,
        2.834,
        13.595,
        -39.047,
        112.484,
        -5.21,
        74.29,
        5,
        42,
        null,
        "off",
        null,
        null,
        null,
        null,
        "TBD",
        "TBD",
        "off"
      ],
      "input_dict": {
        "right_hand_x": null,
        "right_hand_y": null,
        "right_hand_z_mm": 0,
        "right_hand_gesture": null,
        "left_hand_x": null,
        "left_hand_y": null,
        "left_hand_z_mm": 902,
        "left_hand_gesture": null,
        "wrist_accel_x": 0.951,
        "wrist_accel_y": 10.071,
        "wrist_accel_z": 2.834,
        "wrist_gyro_x": 13.595,
        "wrist_gyro_y": -39.047,
        "wrist_gyro_z": 112.484,
        "wrist_pitch": -5.21,
        "wrist_roll": 74.29,
        "camdock_battery_level": 5,
        "wristband_battery_level": 42,
        "fans_battery_level": null,
        "keyboard_input": "off",
        "keyboard_sensor_1_mm": null,
        "keyboard_sensor_2_mm": null,
        "keyboard_sensor_3_mm": null,
        "keyboard_sensor_4_mm": null,
        "charging_dock_input": "TBD",
        "audiodock_input": "TBD",
        "fans_input": "off"
      }
    },
    {
      "t_epoch": 1780053310.7031617,
      "t_rel": 0.7506148815155029,
      "input_array": [
        null,
        null,
        0,
        null,
        null,
        null,
        881,
        null,
        0.52,
        10.042,
        2.903,
        14.671,
        -31.719,
        114.011,
        -2.85,
        73.89,
        5,
        42,
        null,
        "off",
        null,
        null,
        null,
        null,
        "TBD",
        "TBD",
        "off"
      ],
      "input_dict": {
        "right_hand_x": null,
        "right_hand_y": null,
        "right_hand_z_mm": 0,
        "right_hand_gesture": null,
        "left_hand_x": null,
        "left_hand_y": null,
        "left_hand_z_mm": 881,
        "left_hand_gesture": null,
        "wrist_accel_x": 0.52,
        "wrist_accel_y": 10.042,
        "wrist_accel_z": 2.903,
        "wrist_gyro_x": 14.671,
        "wrist_gyro_y": -31.719,
        "wrist_gyro_z": 114.011,
        "wrist_pitch": -2.85,
        "wrist_roll": 73.89,
        "camdock_battery_level": 5,
        "wristband_battery_level": 42,
        "fans_battery_level": null,
        "keyboard_input": "off",
        "keyboard_sensor_1_mm": null,
        "keyboard_sensor_2_mm": null,
        "keyboard_sensor_3_mm": null,
        "keyboard_sensor_4_mm": null,
        "charging_dock_input": "TBD",
        "audiodock_input": "TBD",
        "fans_input": "off"
      }
    },
    {
      "t_epoch": 1780053310.7241569,
      "t_rel": 0.7716100215911865,
      "input_array": [
        null,
        null,
        0,
        null,
        null,
        null,
        946,
        null,
        0.804,
        10.062,
        2.511,
        14.252,
        -37.956,
        114.37,
        -4.45,
        75.98,
        5,
        42,
        null,
        "off",
        null,
        null,
        null,
        null,
        "TBD",
        "TBD",
        "off"
      ],
      "input_dict": {
        "right_hand_x": null,
        "right_hand_y": null,
        "right_hand_z_mm": 0,
        "right_hand_gesture": null,
        "left_hand_x": null,
        "left_hand_y": null,
        "left_hand_z_mm": 946,
        "left_hand_gesture": null,
        "wrist_accel_x": 0.804,
        "wrist_accel_y": 10.062,
        "wrist_accel_z": 2.511,
        "wrist_gyro_x": 14.252,
        "wrist_gyro_y": -37.956,
        "wrist_gyro_z": 114.37,
        "wrist_pitch": -4.45,
        "wrist_roll": 75.98,
        "camdock_battery_level": 5,
        "wristband_battery_level": 42,
        "fans_battery_level": null,
        "keyboard_input": "off",
        "keyboard_sensor_1_mm": null,
        "keyboard_sensor_2_mm": null,
        "keyboard_sensor_3_mm": null,
        "keyboard_sensor_4_mm": null,
        "charging_dock_input": "TBD",
        "audiodock_input": "TBD",
        "fans_input": "off"
      }
    },
    {
      "t_epoch": 1780053310.7451568,
      "t_rel": 0.7926099300384521,
      "input_array": [
        null,
        null,
        0,
        null,
        null,
        null,
        946,
        null,
        0.804,
        10.062,
        2.511,
        14.252,
        -37.956,
        114.37,
        -4.45,
        75.98,
        5,
        42,
        null,
        "off",
        null,
        null,
        null,
        null,
        "TBD",
        "TBD",
        "off"
      ],
      "input_dict": {
        "right_hand_x": null,
        "right_hand_y": null,
        "right_hand_z_mm": 0,
        "right_hand_gesture": null,
        "left_hand_x": null,
        "left_hand_y": null,
        "left_hand_z_mm": 946,
        "left_hand_gesture": null,
        "wrist_accel_x": 0.804,
        "wrist_accel_y": 10.062,
        "wrist_accel_z": 2.511,
        "wrist_gyro_x": 14.252,
        "wrist_gyro_y": -37.956,
        "wrist_gyro_z": 114.37,
        "wrist_pitch": -4.45,
        "wrist_roll": 75.98,
        "camdock_battery_level": 5,
        "wristband_battery_level": 42,
        "fans_battery_level": null,
        "keyboard_input": "off",
        "keyboard_sensor_1_mm": null,
        "keyboard_sensor_2_mm": null,
        "keyboard_sensor_3_mm": null,
        "keyboard_sensor_4_mm": null,
        "charging_dock_input": "TBD",
        "audiodock_input": "TBD",
        "fans_input": "off"
      }
    },
    {
      "t_epoch": 1780053310.7654493,
      "t_rel": 0.8129024505615234,
      "input_array": [
        null,
        null,
        0,
        null,
        null,
        null,
        946,
        null,
        0.735,
        10.081,
        2.53,
        14.358,
        -35.368,
        114.431,
        -4.05,
        75.91,
        5,
        42,
        null,
        "off",
        null,
        null,
        null,
        null,
        "TBD",
        "TBD",
        "off"
      ],
      "input_dict": {
        "right_hand_x": null,
        "right_hand_y": null,
        "right_hand_z_mm": 0,
        "right_hand_gesture": null,
        "left_hand_x": null,
        "left_hand_y": null,
        "left_hand_z_mm": 946,
        "left_hand_gesture": null,
        "wrist_accel_x": 0.735,
        "wrist_accel_y": 10.081,
        "wrist_accel_z": 2.53,
        "wrist_gyro_x": 14.358,
        "wrist_gyro_y": -35.368,
        "wrist_gyro_z": 114.431,
        "wrist_pitch": -4.05,
        "wrist_roll": 75.91,
        "camdock_battery_level": 5,
        "wristband_battery_level": 42,
        "fans_battery_level": null,
        "keyboard_input": "off",
        "keyboard_sensor_1_mm": null,
        "keyboard_sensor_2_mm": null,
        "keyboard_sensor_3_mm": null,
        "keyboard_sensor_4_mm": null,
        "charging_dock_input": "TBD",
        "audiodock_input": "TBD",
        "fans_input": "off"
      }
    },
    {
      "t_epoch": 1780053310.7864377,
      "t_rel": 0.8338909149169922,
      "input_array": [
        null,
        null,
        0,
        null,
        null,
        null,
        946,
        null,
        0.735,
        10.081,
        2.53,
        14.358,
        -35.368,
        114.431,
        -4.05,
        75.91,
        5,
        42,
        null,
        "off",
        null,
        null,
        null,
        null,
        "TBD",
        "TBD",
        "off"
      ],
      "input_dict": {
        "right_hand_x": null,
        "right_hand_y": null,
        "right_hand_z_mm": 0,
        "right_hand_gesture": null,
        "left_hand_x": null,
        "left_hand_y": null,
        "left_hand_z_mm": 946,
        "left_hand_gesture": null,
        "wrist_accel_x": 0.735,
        "wrist_accel_y": 10.081,
        "wrist_accel_z": 2.53,
        "wrist_gyro_x": 14.358,
        "wrist_gyro_y": -35.368,
        "wrist_gyro_z": 114.431,
        "wrist_pitch": -4.05,
        "wrist_roll": 75.91,
        "camdock_battery_level": 5,
        "wristband_battery_level": 42,
        "fans_battery_level": null,
        "keyboard_input": "off",
        "keyboard_sensor_1_mm": null,
        "keyboard_sensor_2_mm": null,
        "keyboard_sensor_3_mm": null,
        "keyboard_sensor_4_mm": null,
        "charging_dock_input": "TBD",
        "audiodock_input": "TBD",
        "fans_input": "off"
      }
    },
    {
      "t_epoch": 1780053310.806991,
      "t_rel": 0.8544442653656006,
      "input_array": [
        null,
        null,
        0,
        null,
        null,
        null,
        946,
        null,
        0.735,
        10.081,
        2.53,
        14.358,
        -35.368,
        114.431,
        -4.05,
        75.91,
        5,
        42,
        null,
        "off",
        null,
        null,
        null,
        null,
        "TBD",
        "TBD",
        "off"
      ],
      "input_dict": {
        "right_hand_x": null,
        "right_hand_y": null,
        "right_hand_z_mm": 0,
        "right_hand_gesture": null,
        "left_hand_x": null,
        "left_hand_y": null,
        "left_hand_z_mm": 946,
        "left_hand_gesture": null,
        "wrist_accel_x": 0.735,
        "wrist_accel_y": 10.081,
        "wrist_accel_z": 2.53,
        "wrist_gyro_x": 14.358,
        "wrist_gyro_y": -35.368,
        "wrist_gyro_z": 114.431,
        "wrist_pitch": -4.05,
        "wrist_roll": 75.91,
        "camdock_battery_level": 5,
        "wristband_battery_level": 42,
        "fans_battery_level": null,
        "keyboard_input": "off",
        "keyboard_sensor_1_mm": null,
        "keyboard_sensor_2_mm": null,
        "keyboard_sensor_3_mm": null,
        "keyboard_sensor_4_mm": null,
        "charging_dock_input": "TBD",
        "audiodock_input": "TBD",
        "fans_input": "off"
      }
    },
    {
      "t_epoch": 1780053310.8270075,
      "t_rel": 0.8744606971740723,
      "input_array": [
        null,
        null,
        0,
        null,
        null,
        null,
        892,
        null,
        0.941,
        10.15,
        2.177,
        15.404,
        -31.414,
        114.454,
        -5.21,
        77.87,
        5,
        42,
        null,
        "off",
        null,
        null,
        null,
        null,
        "TBD",
        "TBD",
        "off"
      ],
      "input_dict": {
        "right_hand_x": null,
        "right_hand_y": null,
        "right_hand_z_mm": 0,
        "right_hand_gesture": null,
        "left_hand_x": null,
        "left_hand_y": null,
        "left_hand_z_mm": 892,
        "left_hand_gesture": null,
        "wrist_accel_x": 0.941,
        "wrist_accel_y": 10.15,
        "wrist_accel_z": 2.177,
        "wrist_gyro_x": 15.404,
        "wrist_gyro_y": -31.414,
        "wrist_gyro_z": 114.454,
        "wrist_pitch": -5.21,
        "wrist_roll": 77.87,
        "camdock_battery_level": 5,
        "wristband_battery_level": 42,
        "fans_battery_level": null,
        "keyboard_input": "off",
        "keyboard_sensor_1_mm": null,
        "keyboard_sensor_2_mm": null,
        "keyboard_sensor_3_mm": null,
        "keyboard_sensor_4_mm": null,
        "charging_dock_input": "TBD",
        "audiodock_input": "TBD",
        "fans_input": "off"
      }
    },
    {
      "t_epoch": 1780053310.847991,
      "t_rel": 0.8954441547393799,
      "input_array": [
        null,
        null,
        0,
        null,
        null,
        null,
        907,
        null,
        0.677,
        10.052,
        2.393,
        14.74,
        -36.467,
        114.484,
        -3.77,
        76.62,
        5,
        42,
        null,
        "off",
        null,
        null,
        null,
        null,
        "TBD",
        "TBD",
        "off"
      ],
      "input_dict": {
        "right_hand_x": null,
        "right_hand_y": null,
        "right_hand_z_mm": 0,
        "right_hand_gesture": null,
        "left_hand_x": null,
        "left_hand_y": null,
        "left_hand_z_mm": 907,
        "left_hand_gesture": null,
        "wrist_accel_x": 0.677,
        "wrist_accel_y": 10.052,
        "wrist_accel_z": 2.393,
        "wrist_gyro_x": 14.74,
        "wrist_gyro_y": -36.467,
        "wrist_gyro_z": 114.484,
        "wrist_pitch": -3.77,
        "wrist_roll": 76.62,
        "camdock_battery_level": 5,
        "wristband_battery_level": 42,
        "fans_battery_level": null,
        "keyboard_input": "off",
        "keyboard_sensor_1_mm": null,
        "keyboard_sensor_2_mm": null,
        "keyboard_sensor_3_mm": null,
        "keyboard_sensor_4_mm": null,
        "charging_dock_input": "TBD",
        "audiodock_input": "TBD",
        "fans_input": "off"
      }
    },
    {
      "t_epoch": 1780053310.868008,
      "t_rel": 0.9154610633850098,
      "input_array": [
        null,
        null,
        0,
        null,
        null,
        null,
        907,
        null,
        0.677,
        10.052,
        2.393,
        14.74,
        -36.467,
        114.484,
        -3.77,
        76.62,
        5,
        42,
        null,
        "off",
        null,
        null,
        null,
        null,
        "TBD",
        "TBD",
        "off"
      ],
      "input_dict": {
        "right_hand_x": null,
        "right_hand_y": null,
        "right_hand_z_mm": 0,
        "right_hand_gesture": null,
        "left_hand_x": null,
        "left_hand_y": null,
        "left_hand_z_mm": 907,
        "left_hand_gesture": null,
        "wrist_accel_x": 0.677,
        "wrist_accel_y": 10.052,
        "wrist_accel_z": 2.393,
        "wrist_gyro_x": 14.74,
        "wrist_gyro_y": -36.467,
        "wrist_gyro_z": 114.484,
        "wrist_pitch": -3.77,
        "wrist_roll": 76.62,
        "camdock_battery_level": 5,
        "wristband_battery_level": 42,
        "fans_battery_level": null,
        "keyboard_input": "off",
        "keyboard_sensor_1_mm": null,
        "keyboard_sensor_2_mm": null,
        "keyboard_sensor_3_mm": null,
        "keyboard_sensor_4_mm": null,
        "charging_dock_input": "TBD",
        "audiodock_input": "TBD",
        "fans_input": "off"
      }
    },
    {
      "t_epoch": 1780053310.888993,
      "t_rel": 0.9364461898803711,
      "input_array": [
        null,
        null,
        0,
        null,
        null,
        null,
        907,
        null,
        0.941,
        10.169,
        2.236,
        15.763,
        -39.818,
        115.484,
        -5.19,
        77.62,
        5,
        42,
        null,
        "off",
        null,
        null,
        null,
        null,
        "TBD",
        "TBD",
        "off"
      ],
      "input_dict": {
        "right_hand_x": null,
        "right_hand_y": null,
        "right_hand_z_mm": 0,
        "right_hand_gesture": null,
        "left_hand_x": null,
        "left_hand_y": null,
        "left_hand_z_mm": 907,
        "left_hand_gesture": null,
        "wrist_accel_x": 0.941,
        "wrist_accel_y": 10.169,
        "wrist_accel_z": 2.236,
        "wrist_gyro_x": 15.763,
        "wrist_gyro_y": -39.818,
        "wrist_gyro_z": 115.484,
        "wrist_pitch": -5.19,
        "wrist_roll": 77.62,
        "camdock_battery_level": 5,
        "wristband_battery_level": 42,
        "fans_battery_level": null,
        "keyboard_input": "off",
        "keyboard_sensor_1_mm": null,
        "keyboard_sensor_2_mm": null,
        "keyboard_sensor_3_mm": null,
        "keyboard_sensor_4_mm": null,
        "charging_dock_input": "TBD",
        "audiodock_input": "TBD",
        "fans_input": "off"
      }
    },
    {
      "t_epoch": 1780053310.9095001,
      "t_rel": 0.9569532871246338,
      "input_array": [
        null,
        null,
        0,
        null,
        null,
        null,
        1040,
        null,
        0.853,
        10.071,
        2.432,
        17.9,
        -36.994,
        114.713,
        -4.69,
        76.41,
        5,
        42,
        null,
        "off",
        null,
        null,
        null,
        null,
        "TBD",
        "TBD",
        "off"
      ],
      "input_dict": {
        "right_hand_x": null,
        "right_hand_y": null,
        "right_hand_z_mm": 0,
        "right_hand_gesture": null,
        "left_hand_x": null,
        "left_hand_y": null,
        "left_hand_z_mm": 1040,
        "left_hand_gesture": null,
        "wrist_accel_x": 0.853,
        "wrist_accel_y": 10.071,
        "wrist_accel_z": 2.432,
        "wrist_gyro_x": 17.9,
        "wrist_gyro_y": -36.994,
        "wrist_gyro_z": 114.713,
        "wrist_pitch": -4.69,
        "wrist_roll": 76.41,
        "camdock_battery_level": 5,
        "wristband_battery_level": 42,
        "fans_battery_level": null,
        "keyboard_input": "off",
        "keyboard_sensor_1_mm": null,
        "keyboard_sensor_2_mm": null,
        "keyboard_sensor_3_mm": null,
        "keyboard_sensor_4_mm": null,
        "charging_dock_input": "TBD",
        "audiodock_input": "TBD",
        "fans_input": "off"
      }
    },
    {
      "t_epoch": 1780053310.9295015,
      "t_rel": 0.9769546985626221,
      "input_array": [
        null,
        null,
        0,
        null,
        null,
        null,
        1040,
        null,
        0.608,
        10.13,
        2.206,
        18.0,
        -33.49,
        114.072,
        -3.36,
        77.72,
        5,
        42,
        null,
        "off",
        null,
        null,
        null,
        null,
        "TBD",
        "TBD",
        "off"
      ],
      "input_dict": {
        "right_hand_x": null,
        "right_hand_y": null,
        "right_hand_z_mm": 0,
        "right_hand_gesture": null,
        "left_hand_x": null,
        "left_hand_y": null,
        "left_hand_z_mm": 1040,
        "left_hand_gesture": null,
        "wrist_accel_x": 0.608,
        "wrist_accel_y": 10.13,
        "wrist_accel_z": 2.206,
        "wrist_gyro_x": 18.0,
        "wrist_gyro_y": -33.49,
        "wrist_gyro_z": 114.072,
        "wrist_pitch": -3.36,
        "wrist_roll": 77.72,
        "camdock_battery_level": 5,
        "wristband_battery_level": 42,
        "fans_battery_level": null,
        "keyboard_input": "off",
        "keyboard_sensor_1_mm": null,
        "keyboard_sensor_2_mm": null,
        "keyboard_sensor_3_mm": null,
        "keyboard_sensor_4_mm": null,
        "charging_dock_input": "TBD",
        "audiodock_input": "TBD",
        "fans_input": "off"
      }
    },
    {
      "t_epoch": 1780053310.9505014,
      "t_rel": 0.9979546070098877,
      "input_array": [
        null,
        null,
        0,
        null,
        null,
        null,
        1040,
        null,
        0.608,
        10.13,
        2.206,
        18.0,
        -33.49,
        114.072,
        -3.36,
        77.72,
        5,
        42,
        null,
        "off",
        null,
        null,
        null,
        null,
        "TBD",
        "TBD",
        "off"
      ],
      "input_dict": {
        "right_hand_x": null,
        "right_hand_y": null,
        "right_hand_z_mm": 0,
        "right_hand_gesture": null,
        "left_hand_x": null,
        "left_hand_y": null,
        "left_hand_z_mm": 1040,
        "left_hand_gesture": null,
        "wrist_accel_x": 0.608,
        "wrist_accel_y": 10.13,
        "wrist_accel_z": 2.206,
        "wrist_gyro_x": 18.0,
        "wrist_gyro_y": -33.49,
        "wrist_gyro_z": 114.072,
        "wrist_pitch": -3.36,
        "wrist_roll": 77.72,
        "camdock_battery_level": 5,
        "wristband_battery_level": 42,
        "fans_battery_level": null,
        "keyboard_input": "off",
        "keyboard_sensor_1_mm": null,
        "keyboard_sensor_2_mm": null,
        "keyboard_sensor_3_mm": null,
        "keyboard_sensor_4_mm": null,
        "charging_dock_input": "TBD",
        "audiodock_input": "TBD",
        "fans_input": "off"
      }
    }
  ],
  "raw_device_state_at_end": {
    "t_ms": 2762734,
    "sequence": 17611,
    "antenna_mac": "30:ED:A0:BB:97:EC",
    "devices": {
      "wristband": {
        "status": "ok",
        "battery_level": 42,
        "battery_voltage": 3.68,
        "battery": {
          "status": "ok",
          "percent": 42,
          "voltage_v": 3.68,
          "adc_raw": 2554,
          "age_ms": 7660
        },
        "sequence": 63986,
        "t_ms": 3903199,
        "accel": {
          "x": 0.735,
          "y": 10.199,
          "z": 2.079
        },
        "gyro": {
          "x": 16.565,
          "y": -33.711,
          "z": 112.973
        },
        "pitch": -4.05,
        "roll": 78.51,
        "yaw": null
      },
      "camdock": {
        "status": "ok",
        "battery_level": 5,
        "battery_voltage": 6.613,
        "battery": {
          "status": "ok",
          "percent": 5,
          "voltage_v": 6.613,
          "adc_raw": 2564,
          "age_ms": 24
        },
        "sequence": 18536,
        "t_ms": 2779142,
        "tof": {
          "left_mm": 935,
          "right_mm": 0
        },
        "active_target": "none"
      },
      "keyboard": {
        "status": "not_connected",
        "input": "off",
        "battery_level": null,
        "sequence": null,
        "t_ms": null,
        "tof": {
          "sensor_1_mm": null,
          "sensor_2_mm": null,
          "sensor_3_mm": null
        },
        "valid": {
          "sensor_1": false,
          "sensor_2": false,
          "sensor_3": false
        }
      },
      "charging_dock": {
        "status": "TBD",
        "input": "TBD",
        "battery_level": null
      },
      "audiodock": {
        "status": "not_connected",
        "battery_level": null,
        "sequence": null,
        "t_ms": null,
        "clap_detected": false,
        "clap_type": null
      },
      "fans": {
        "status": "not_connected",
        "input": "off",
        "battery_level": null,
        "battery_voltage": null,
        "battery": {
          "status": "not_connected",
          "percent": null,
          "voltage_v": null,
          "adc_raw": null,
          "age_ms": null
        },
        "fan_on": false,
        "sequence": null,
        "t_ms": null,
        "last_command_sequence": null,
        "temps": {
          "sensor_1_c": null,
          "sensor_2_c": null
        }
      }
    }
  },
  "hand_state_at_end": {
    "right": {
      "visible": false,
      "x": null,
      "y": null,
      "score": 0.0,
      "gesture": "none"
    },
    "left": {
      "visible": false,
      "x": null,
      "y": null,
      "score": 0.0,
      "gesture": "none"
    }
  }
}
